nonebot_plugin_QRrender/__init__.py
nonebot_plugin_QRrender/config.py
nonebot_plugin_QRrender-0.0.6.dist-info/LICENSE.txt
nonebot_plugin_QRrender-0.0.6.dist-info/METADATA
nonebot_plugin_QRrender-0.0.6.dist-info/WHEEL
nonebot_plugin_QRrender-0.0.6.dist-info/top_level.txt
nonebot_plugin_QRrender-0.0.6.dist-info/RECORD
