Metadata-Version: 2.1
Name: nonebot-plugin-QRrender
Version: 0.0.6
Summary: 将文本转为二维码，可自定义样式
Home-page: https://github.com/Funny1Potato/nonebot-plugin-QRrender
Author: Funny1Potato
Author-email: funny_potato@126.com
Classifier: Programming Language :: Python :: 3
Classifier: License :: OSI Approved :: MIT License
Classifier: Operating System :: OS Independent
Requires-Python: >=3.9
License-File: LICENSE.txt
Requires-Dist: nonebot2>=2.3
Requires-Dist: nonebot-adapter-onebot>=2.4
Requires-Dist: httpx>=0.27
Requires-Dist: amzqr>=0.0.1
Requires-Dist: nonebot-plugin-localstore>=0.7
